<?xml version="1.0" ?>
<Voxelyze_Sim_Result Version="1.0">
    <Fitness>
        <NormFinalDist>15.5308</NormFinalDist>
        <NormRegimeDist>7.03532</NormRegimeDist>
        <NormFrozenDist>0</NormFrozenDist>
        <FinalDist>15.5308</FinalDist>
        <finalDistY>15.4888</finalDistY>
        <AnteriorDist>17.9894</AnteriorDist>
        <PosteriorDist>7.03532</PosteriorDist>
        <AnteriorY>19.9787</AnteriorY>
        <PosteriorY>2.29999</PosteriorY>
        <EndOfLifePosteriorY>0</EndOfLifePosteriorY>
        <FallAdjPostY>0</FallAdjPostY>
        <NumNonFeetTouchingFloor>0</NumNonFeetTouchingFloor>
        <NumTouchingFloor>18</NumTouchingFloor>
        <Lifetime>60</Lifetime>
        <FoundNeedleInHaystack>1</FoundNeedleInHaystack>
        <PushDist>4.31901</PushDist>
        <PushRot>-0.00226291</PushRot>
        <RotVel>1.27508e-13</RotVel>
    </Fitness>
</Voxelyze_Sim_Result>
