<?xml version="1.0" ?>
<Voxelyze_Sim_Result Version="1.0">
    <Fitness>
        <NormFinalDist>0.776615</NormFinalDist>
        <NormRegimeDist>0.241939</NormRegimeDist>
        <NormFrozenDist>0</NormFrozenDist>
        <FinalDist>0.776615</FinalDist>
        <finalDistY>-0.458276</finalDistY>
        <AnteriorDist>2.67254</AnteriorDist>
        <PosteriorDist>0.241939</PosteriorDist>
        <AnteriorY>2.51844</AnteriorY>
        <PosteriorY>0.974986</PosteriorY>
        <EndOfLifePosteriorY>0</EndOfLifePosteriorY>
        <FallAdjPostY>0</FallAdjPostY>
        <NumNonFeetTouchingFloor>0</NumNonFeetTouchingFloor>
        <NumTouchingFloor>8</NumTouchingFloor>
        <Lifetime>60.0005</Lifetime>
        <FoundNeedleInHaystack>1</FoundNeedleInHaystack>
        <PushDist>0.0755868</PushDist>
        <PushRot>5.87763e-05</PushRot>
        <RotVel>-7.59262e-06</RotVel>
    </Fitness>
</Voxelyze_Sim_Result>
