<?xml version="1.0" ?>
<Voxelyze_Sim_Result Version="1.0">
    <Fitness>
        <NormFinalDist>1.3567</NormFinalDist>
        <NormRegimeDist>0.657067</NormRegimeDist>
        <NormFrozenDist>0</NormFrozenDist>
        <FinalDist>1.3567</FinalDist>
        <finalDistY>0.275366</finalDistY>
        <AnteriorDist>3.29257</AnteriorDist>
        <PosteriorDist>0.657067</PosteriorDist>
        <AnteriorY>3.91098</AnteriorY>
        <PosteriorY>0.815677</PosteriorY>
        <EndOfLifePosteriorY>0</EndOfLifePosteriorY>
        <FallAdjPostY>0</FallAdjPostY>
        <NumNonFeetTouchingFloor>0</NumNonFeetTouchingFloor>
        <NumTouchingFloor>8</NumTouchingFloor>
        <Lifetime>60.0005</Lifetime>
        <FoundNeedleInHaystack>0</FoundNeedleInHaystack>
        <PushDist>0</PushDist>
        <PushRot>0</PushRot>
        <RotVel>0</RotVel>
    </Fitness>
</Voxelyze_Sim_Result>
