<?xml version="1.0" ?>
<Voxelyze_Sim_Result Version="1.0">
    <Fitness>
        <NormFinalDist>5.00647</NormFinalDist>
        <NormRegimeDist>3.30553</NormRegimeDist>
        <NormFrozenDist>0</NormFrozenDist>
        <FinalDist>5.00647</FinalDist>
        <finalDistY>-0.457469</finalDistY>
        <AnteriorDist>7.13222</AnteriorDist>
        <PosteriorDist>3.30553</PosteriorDist>
        <AnteriorY>2.97451</AnteriorY>
        <PosteriorY>-0.164049</PosteriorY>
        <EndOfLifePosteriorY>0</EndOfLifePosteriorY>
        <FallAdjPostY>0</FallAdjPostY>
        <NumNonFeetTouchingFloor>0</NumNonFeetTouchingFloor>
        <NumTouchingFloor>11</NumTouchingFloor>
        <Lifetime>60.0005</Lifetime>
        <FoundNeedleInHaystack>0</FoundNeedleInHaystack>
        <PushDist>0</PushDist>
        <PushRot>0</PushRot>
        <RotVel>0</RotVel>
    </Fitness>
</Voxelyze_Sim_Result>
