<?xml version="1.0" ?>
<Voxelyze_Sim_Result Version="1.0">
    <Fitness>
        <NormFinalDist>14.6999</NormFinalDist>
        <NormRegimeDist>3.79865</NormRegimeDist>
        <NormFrozenDist>0</NormFrozenDist>
        <FinalDist>14.6999</FinalDist>
        <finalDistY>-5.70532</finalDistY>
        <AnteriorDist>17.0813</AnteriorDist>
        <PosteriorDist>3.79865</PosteriorDist>
        <AnteriorY>2.5</AnteriorY>
        <PosteriorY>-6.04154</PosteriorY>
        <EndOfLifePosteriorY>0</EndOfLifePosteriorY>
        <FallAdjPostY>0</FallAdjPostY>
        <NumNonFeetTouchingFloor>0</NumNonFeetTouchingFloor>
        <NumTouchingFloor>12</NumTouchingFloor>
        <Lifetime>60.0005</Lifetime>
        <FoundNeedleInHaystack>0</FoundNeedleInHaystack>
        <PushDist>0</PushDist>
        <PushRot>0</PushRot>
        <RotVel>0</RotVel>
    </Fitness>
</Voxelyze_Sim_Result>
